diffpy/__init__.py
diffpy/labpdfproc/__init__.py
diffpy/labpdfproc/functions.py
diffpy/labpdfproc/labpdfprocapp.py
diffpy/labpdfproc/mud_calculator.py
diffpy/labpdfproc/tools.py
diffpy/labpdfproc/version.py
diffpy/labpdfproc/data/coefficient_list.csv
diffpy/labpdfproc/data/inverse_cve.xy
diffpy.labpdfproc-0.2.0.dist-info/AUTHORS.rst
diffpy.labpdfproc-0.2.0.dist-info/LICENSE.rst
diffpy.labpdfproc-0.2.0.dist-info/METADATA
diffpy.labpdfproc-0.2.0.dist-info/WHEEL
diffpy.labpdfproc-0.2.0.dist-info/entry_points.txt
diffpy.labpdfproc-0.2.0.dist-info/top_level.txt
diffpy.labpdfproc-0.2.0.dist-info/RECORD
