Metadata-Version: 2.1
Name: diffpy.labpdfproc
Version: 0.2.0
Summary: Tools for processing x-ray powder diffraction data from laboratory sources.
Author-email: "Simon J.L. Billinge group" <simon.billinge@gmail.com>
Maintainer-email: "Simon J.L. Billinge group" <simon.billinge@gmail.com>
Project-URL: Homepage, https://github.com/diffpy/diffpy.labpdfproc/
Project-URL: Issues, https://github.com/diffpy/diffpy.labpdfproc/issues/
Keywords: powder xrd,absorption correction,pdf,diffpy
Classifier: Development Status :: 5 - Production/Stable
Classifier: Environment :: Console
Classifier: Intended Audience :: Developers
Classifier: Intended Audience :: Science/Research
Classifier: License :: OSI Approved :: BSD License
Classifier: Operating System :: MacOS :: MacOS X
Classifier: Operating System :: Microsoft :: Windows
Classifier: Operating System :: POSIX
Classifier: Operating System :: Unix
Classifier: Programming Language :: Python :: 3.11
Classifier: Programming Language :: Python :: 3.12
Classifier: Programming Language :: Python :: 3.13
Classifier: Topic :: Scientific/Engineering :: Physics
Classifier: Topic :: Scientific/Engineering :: Chemistry
Requires-Python: <3.14,>=3.11
License-File: LICENSE.rst
License-File: AUTHORS.rst
Requires-Dist: numpy
Requires-Dist: diffpy.utils
Requires-Dist: pandas
Requires-Dist: scipy
